{"cameraMode":{"drawMode":0,"name":"Shaded","section":"Shading Mode"},"sceneLighting":false,"audioPlay":false,"sceneViewState":{"showFog":true,"showMaterialUpdate":false,"showSkybox":false,"showFlares":true,"showImageEffects":true,"showParticleSystems":true},"in2DMode":false,"pivot":{"x":-0.4321914315223694,"y":0.9045243263244629,"z":-11.600035667419434},"rotation":{"x":-0.004673469811677933,"y":0.9770615696907044,"z":-0.021520664915442468,"w":-0.21186019480228425},"size":4.30275821685791,"orthographic":false}